catkin_tools_python/__init__.py
catkin_tools_python/create_pypi_gbp.py
catkin_tools_python/create_python_package_xmls.py
catkin_tools_python/filters.py
catkin_tools_python/fix_python_script_shebangs.py
catkin_tools_python/job.py
catkin_tools_python-0.1.1.dist-info/DESCRIPTION.rst
catkin_tools_python-0.1.1.dist-info/METADATA
catkin_tools_python-0.1.1.dist-info/RECORD
catkin_tools_python-0.1.1.dist-info/WHEEL
catkin_tools_python-0.1.1.dist-info/entry_points.txt
catkin_tools_python-0.1.1.dist-info/metadata.json
catkin_tools_python-0.1.1.dist-info/top_level.txt
