Metadata-Version: 2.0
Name: catkin-tools-python
Version: 0.1.1
Summary: Python buildtype plugin for catkin_tools.
Home-page: http://catkin-tools-python.readthedocs.org/
Author: Mike Purvis
Author-email: mike@uwmike.com
License: Apache 2.0
Keywords: catkin
Platform: UNKNOWN
Classifier: Environment :: Console
Classifier: Intended Audience :: Developers
Classifier: License :: OSI Approved :: Apache Software License
Classifier: Programming Language :: Python
Requires-Dist: catkin-tools (>=0.4.4)
Requires-Dist: empy
Requires-Dist: pkginfo (>=0.9.1)
